tri_token/__init__.py
tri.token-4.0.0.dist-info/AUTHORS.rst
tri.token-4.0.0.dist-info/LICENSE
tri.token-4.0.0.dist-info/METADATA
tri.token-4.0.0.dist-info/WHEEL
tri.token-4.0.0.dist-info/top_level.txt
tri.token-4.0.0.dist-info/RECORD
