Metadata-Version: 2.1
Name: tri.token
Version: 4.0.0
Summary: tri.token provides enriched enum functionality
Home-page: https://github.com/TriOptima/tri.token
Author: Johan Lübcke
Author-email: johan.lubcke@trioptima.com
License: BSD
Keywords: tri.token
Platform: UNKNOWN
Classifier: Development Status :: 5 - Production/Stable
Classifier: Intended Audience :: Developers
Classifier: License :: OSI Approved :: BSD License
Classifier: Natural Language :: English
Classifier: Programming Language :: Python :: 3
Classifier: Programming Language :: Python :: 3.6
Requires-Dist: tri.declarative (<6.0.0,>=4.0.0)
Requires-Dist: tri.struct (<5.0.0,>=3.0.0)
Requires-Dist: prettytable
